[{"id": 1, "like": -1, "comment": 0, "link": "https://instagram.com/p/Chdxzt9pSdt"}, {"id": 2, "like": -1, "comment": 0, "link": "https://instagram.com/p/Chb7I7spdHN"}, {"id": 3, "like": -1, "comment": 2, "link": "https://instagram.com/p/ChJXObppHSn"}, {"id": 4, "like": 1726, "comment": 24, "link": "https://instagram.com/p/Cg8-IfOpvk-"}, {"id": 5, "like": -1, "comment": 0, "link": "https://instagram.com/p/Cg87Eg6JIAB"}, {"id": 6, "like": 1663, "comment": 19, "link": "https://instagram.com/p/Cgtj8uTptPZ"}, {"id": 7, "like": -1, "comment": 0, "link": "https://instagram.com/p/CgtijNUpdEL"}, {"id": 8, "like": 2434, "comment": 17, "link": "https://instagram.com/p/CgrDQOvJiGc"}, {"id": 9, "like": -1, "comment": 5, "link": "https://instagram.com/p/CgmAZgzpH2e"}, {"id": 10, "like": 2101, "comment": 12, "link": "https://instagram.com/p/CgjU-XPJK3Y"}, {"id": 11, "like": -1, "comment": 14, "link": "https://instagram.com/p/CgTHl-NJjh8"}, {"id": 12, "like": 2822, "comment": 31, "link": "https://instagram.com/p/CgCFWbvpMAT"}]