[{"id": 1, "like": 11224, "comment": 191, "link": "https://instagram.com/p/CT8tCD3lp4S"}, {"id": 2, "like": 534, "comment": 23, "link": "https://instagram.com/p/CgL4SEWgLbB"}, {"id": 3, "like": -1, "comment": 0, "link": "https://instagram.com/p/CgL1tVkrMBx"}, {"id": 4, "like": -1, "comment": 12, "link": "https://instagram.com/p/CfmIIhKvnOv"}, {"id": 5, "like": 8043, "comment": 66, "link": "https://instagram.com/p/CfQimkWhdQH"}, {"id": 6, "like": -1, "comment": 3, "link": "https://instagram.com/p/CenuSf9rslz"}, {"id": 7, "like": -1, "comment": 0, "link": "https://instagram.com/p/CeclFlovt6e"}, {"id": 8, "like": -1, "comment": 4, "link": "https://instagram.com/p/CebHYEjLakW"}, {"id": 9, "like": -1, "comment": 19, "link": "https://instagram.com/p/CeRGGGFPlfn"}, {"id": 10, "like": 2420, "comment": 26, "link": "https://instagram.com/p/Cd-XLqbrcZl"}, {"id": 11, "like": -1, "comment": 0, "link": "https://instagram.com/p/CdliVCCvUPz"}, {"id": 12, "like": 1847, "comment": 32, "link": "https://instagram.com/p/CdiYoxUrqY4"}]