[{"id": 1, "like": 68228, "comment": 595, "link": "https://instagram.com/p/ChhznKchCre"}, {"id": 2, "like": 51447, "comment": 495, "link": "https://instagram.com/p/CherZA1Bz_v"}, {"id": 3, "like": 3623, "comment": 45, "link": "https://instagram.com/p/ChPBkAMPZJm"}, {"id": 4, "like": 13116, "comment": 57, "link": "https://instagram.com/p/Cgv0ApOr8no"}, {"id": 5, "like": 46802, "comment": 336, "link": "https://instagram.com/p/CgGiJGbrhxQ"}, {"id": 6, "like": 42855, "comment": 435, "link": "https://instagram.com/p/CfYxs9SBi6z"}, {"id": 7, "like": 49920, "comment": 423, "link": "https://instagram.com/p/Ce0ASbjrTqZ"}, {"id": 8, "like": 18930, "comment": 227, "link": "https://instagram.com/p/CebKdnJhlQq"}, {"id": 9, "like": 26051, "comment": 182, "link": "https://instagram.com/p/CeVe96DL6dH"}, {"id": 10, "like": 26402, "comment": 259, "link": "https://instagram.com/p/Cdfwb_lBPpG"}, {"id": 11, "like": 104597, "comment": 448, "link": "https://instagram.com/p/CdIrCnRvP4i"}, {"id": 12, "like": 24111, "comment": 231, "link": "https://instagram.com/p/CdA93LVBb1q"}]